tbldo/__init__.py
tbldo/__main__.py
tbldo-1.0.5.dist-info/LICENSE
tbldo-1.0.5.dist-info/METADATA
tbldo-1.0.5.dist-info/WHEEL
tbldo-1.0.5.dist-info/entry_points.txt
tbldo-1.0.5.dist-info/top_level.txt
tbldo-1.0.5.dist-info/RECORD
