Metadata-Version: 2.1
Name: tbldo
Version: 1.0.5
Summary: Run a linux command with varying inputs according to tabular data
Author-email: thecodedog <elcodedog@gmail.com>
License: MIT License
Keywords: tabular,linux,command,configuration
Classifier: License :: OSI Approved :: MIT License
Classifier: Programming Language :: Python
Classifier: Programming Language :: Python :: 3
Requires-Python: >=3.10
License-File: LICENSE
Requires-Dist: pandas (==1.5.3)
Requires-Dist: SQLAlchemy (==2.0.4)
